LocToWeatherAPI/API.py
LocToWeatherAPI/__init__.py
LocToWeatherAPI/api_server.py
LocToWeatherAPI/main.py
LocToWeatherAPI-1.0.0.dist-info/LICENSE
LocToWeatherAPI-1.0.0.dist-info/METADATA
LocToWeatherAPI-1.0.0.dist-info/WHEEL
LocToWeatherAPI-1.0.0.dist-info/top_level.txt
LocToWeatherAPI-1.0.0.dist-info/RECORD
