Metadata-Version: 2.1
Name: LocToWeatherAPI
Version: 1.0.0
Summary: Package for Generating weather data from place name and/or date with included browsable API
Home-page: https://github.com/KinjalDas/Location_To_Climate_API
Author: Kinjal Das
Author-email: kinjal.das86@gmail.com
License: UNKNOWN
Platform: UNKNOWN
Classifier: Programming Language :: Python :: 3
Classifier: License :: OSI Approved :: Apache Software License
Classifier: Operating System :: OS Independent
Requires-Python: >=3.6
